pyminifier_bundled/__init__.py
pyminifier_bundled/__main__.py
pyminifier_bundled/analyze.py
pyminifier_bundled/compression.py
pyminifier_bundled/important_information_about_license.py
pyminifier_bundled/minification.py
pyminifier_bundled/obfuscate.py
pyminifier_bundled/token_utils.py
unitgrade_private/__init__.py
unitgrade_private/deployment.py
unitgrade_private/docker_helpers.py
unitgrade_private/hidden_create_files.py
unitgrade_private/hidden_gather_upload.py
unitgrade_private/run.py
unitgrade_private/token_loader.py
unitgrade_private/utils.py
unitgrade_private/version.py
unitgrade_private/autolab/__init__.py
unitgrade_private/autolab/autolab.py
unitgrade_private/autolab/lab_template/Makefile
unitgrade_private/autolab/lab_template/autograde-Makefile
unitgrade_private/autolab/lab_template/hello.rb
unitgrade_private/autolab/lab_template/hello.yml
unitgrade_private/autolab/lab_template/src/Makefile
unitgrade_private/autolab/lab_template/src/README
unitgrade_private/autolab/lab_template/src/driver.sh
unitgrade_private/autolab/lab_template/src/driver_python.py
unitgrade_private/pipelines/__init__.py
unitgrade_private/pipelines/digital_exam.py
unitgrade_private/pipelines/dtulearn.py
unitgrade_private/pipelines/dummy_handins.py
unitgrade_private/plagiarism/__init__.py
unitgrade_private/plagiarism/mossit.py
unitgrade_private/plagiarism/utils.py
unitgrade_devel-0.1.64.dist-info/LICENSE
unitgrade_devel-0.1.64.dist-info/METADATA
unitgrade_devel-0.1.64.dist-info/WHEEL
unitgrade_devel-0.1.64.dist-info/top_level.txt
unitgrade_devel-0.1.64.dist-info/RECORD
