Metadata-Version: 2.1
Name: unitgrade-devel
Version: 0.1.64
Summary: A set of tools to develop unitgrade tests and reports and later evaluate them
Home-page: https://lab.compute.dtu.dk/tuhe/unitgrade_private
Author: Tue Herlau
Author-email: tuhe@dtu.dk
License: MIT
Project-URL: Bug Tracker, https://lab.compute.dtu.dk/tuhe/unitgrade_private/issues
Classifier: Programming Language :: Python :: 3
Classifier: License :: OSI Approved :: MIT License
Classifier: Operating System :: OS Independent
Requires-Python: >=3.8
License-File: LICENSE
Requires-Dist: unitgrade
Requires-Dist: numpy
Requires-Dist: codesnipper
Requires-Dist: tabulate
Requires-Dist: tqdm
Requires-Dist: pyfiglet
Requires-Dist: jinja2
Requires-Dist: colorama
Requires-Dist: coverage
Requires-Dist: mosspy
